README.md
setup.py
alibabacloud_sdk_openplatform20191219/__init__.py
alibabacloud_sdk_openplatform20191219/client.py
alibabacloud_sdk_openplatform20191219/models.py
alibabacloud_sdk_openplatform20191219.egg-info/PKG-INFO
alibabacloud_sdk_openplatform20191219.egg-info/SOURCES.txt
alibabacloud_sdk_openplatform20191219.egg-info/dependency_links.txt
alibabacloud_sdk_openplatform20191219.egg-info/requires.txt
alibabacloud_sdk_openplatform20191219.egg-info/top_level.txt