Metadata-Version: 1.1
Name: alibabacloud-sdk-openplatform20191219
Version: 1.0.0
Summary: Alibaba Cloud OpenPlatform SDK for Python
Home-page: https://github.com/aliyun/alibabacloud-sdk
Author: Alibaba Cloud SDK
Author-email: sdk-team@alibabacloud.com
License: Apache
Keywords: ${name}
Platform: any
Classifier: Development Status :: 4 - Beta
Classifier: Intended Audience :: Developers
Classifier: License :: OSI Approved :: Apache Software License
Classifier: Programming Language :: Python
Classifier: Programming Language :: Python :: 3
Classifier: Programming Language :: Python :: 3.3
Classifier: Programming Language :: Python :: 3.4
Classifier: Programming Language :: Python :: 3.5
Classifier: Programming Language :: Python :: 3.6
Classifier: Topic :: Software Development
